takit/__init__.py
takit/__version__.py
takit/enums.py
takit/validation.py
takit/data/__init__.py
takit/data/base.py
takit/data/binance_client.py
takit/indicators/__init__.py
takit/indicators/momentum/__init__.py
takit/indicators/momentum/ma_deviation.py
takit/indicators/momentum/ma_streak.py
takit/indicators/momentum/macd.py
takit/indicators/momentum/rsi.py
takit/indicators/momentum/williams_r.py
takit/indicators/performance/__init__.py
takit/indicators/performance/drawdown.py
takit/indicators/performance/relative_change.py
takit/indicators/trend/__init__.py
takit/indicators/trend/ma.py
takit/indicators/volatility/__init__.py
takit/indicators/volatility/atr.py
takit/indicators/volatility/bollinger_bands.py
takit/indicators/volatility/donchian_channel.py
takit/signals/__init__.py
takit/signals/cycles/__init__.py
takit/signals/cycles/btc.py
takit/signals/trend/__init__.py
takit/signals/trend/ma_cross.py
takit/signals/trend/trend_rider.py
takit/signals/volatility/__init__.py
takit/signals/volatility/bb_squeeze.py
takit/signals/volatility/williams_vix_fix.py
takit/util/base.py
takit/util/date.py
takit-0.1.0.dist-info/METADATA
takit-0.1.0.dist-info/WHEEL
takit-0.1.0.dist-info/licenses/LICENSE
takit-0.1.0.dist-info/RECORD
