Metadata-Version: 2.4
Name: takit
Version: 0.1.0
Summary: Technical analysis library for financial data.
Project-URL: Homepage, https://github.com/ivarurdalen/takit
Project-URL: Source, https://github.com/ivarurdalen/takit
Project-URL: Changelog, https://github.com/ivarurdalen/takit/blob/main/CHANGELOG.md
Author-email: ivarurdalen <ivar.urdalen@gmail.com>
License-Expression: MIT
License-File: LICENSE
Classifier: Intended Audience :: Developers
Classifier: License :: OSI Approved :: MIT License
Classifier: Programming Language :: Python :: 3 :: Only
Classifier: Programming Language :: Python :: 3.10
Classifier: Programming Language :: Python :: 3.11
Classifier: Programming Language :: Python :: 3.12
Classifier: Programming Language :: Python :: 3.13
Classifier: Topic :: Software Development :: Libraries :: Python Modules
Requires-Python: >=3.10
Requires-Dist: pandas>=2
Requires-Dist: pandera>=0.25.0
Requires-Dist: pyarrow>=21.0.0
Requires-Dist: pydantic>=2
Provides-Extra: cli
Requires-Dist: typer; extra == 'cli'
Provides-Extra: data
Requires-Dist: binance-connector; extra == 'data'
